diamond_add_taxonomy/__init__.py
diamond_add_taxonomy/cli.py
diamond_add_taxonomy/taxid_utils.py
diamond_add_taxonomy-0.1.1.dist-info/entry_points.txt
diamond_add_taxonomy-0.1.1.dist-info/LICENSE
diamond_add_taxonomy-0.1.1.dist-info/WHEEL
diamond_add_taxonomy-0.1.1.dist-info/METADATA
diamond_add_taxonomy-0.1.1.dist-info/RECORD
